{
  "autoplayBgm": true,
  "autoplayBgs": true,
  "battleback1Name": "Tent",
  "battleback2Name": "Tent",
  "bgm": {
    "name": "map_adon",
    "pan": 0,
    "pitch": 100,
    "volume": 60
  },
  "bgs": {
    "name": "",
    "pan": 0,
    "pitch": 100,
    "volume": 80
  },
  "disableDashing": false,
  "displayName": "Tent",
  "encounterList": [],
  "encounterStep": 30,
  "height": 12,
  "note": "<Unlocked>",
  "parallaxLoopX": false,
  "parallaxLoopY": false,
  "parallaxName": "",
  "parallaxShow": false,
  "parallaxSx": 0,
  "parallaxSy": 0,
  "scrollType": 0,
  "specifyBattleback": false,
  "tilesetId": 13,
  "width": 7,
  "data": [
    1536,
    1536,
    1536,
    1536,
    1536,
    1536,
    1536,
    1536,
    1536,
    1536,
    1536,
    1536,
    1536,
    1536,
    1536,
    1536,
    1536,
    1536,
    1536,
    1536,
    1536,
    1536,
    1536,
    1536,
    1536,
    1536,
    1536,
    1536,
    1536,
    1536,
    1536,
    1536,
    1536,
    1536,
    1536,
    1536,
    1536,
    1589,
    1589,
    1589,
    1536,
    1536,
    1536,
    1536,
    1589,
    1589,
    1589,
    1536,
    1536,
    1536,
    1536,
    1589,
    1589,
    1589,
    1536,
    1536,
    1536,
    1536,
    1589,
    1589,
    1589,
    1536,
    1536,
    1536,
    1536,
    1589,
    1589,
    1589,
    1536,
    1536,
    1536,
    1536,
    1536,
    1536,
    1536,
    1536,
    1536,
    1536,
    1536,
    1536,
    1536,
    1536,
    1536,
    1536,
    0,
    0,
    0,
    0,
    0,
    0,
    0,
    0,
    0,
    0,
    0,
    0,
    0,
    0,
    0,
    0,
    0,
    0,
    0,
    0,
    0,
    0,
    0,
    0,
    0,
    0,
    0,
    0,
    0,
    0,
    0,
    0,
    0,
    0,
    0,
    0,
    0,
    0,
    0,
    0,
    0,
    0,
    0,
    0,
    0,
    0,
    3194,
    0,
    0,
    0,
    0,
    0,
    0,
    3196,
    0,
    0,
    0,
    0,
    0,
    0,
    0,
    0,
    0,
    0,
    0,
    0,
    0,
    0,
    0,
    0,
    0,
    0,
    0,
    0,
    0,
    0,
    0,
    0,
    0,
    0,
    0,
    0,
    0,
    0,
    0,
    0,
    0,
    0,
    0,
    0,
    0,
    0,
    0,
    0,
    0,
    0,
    0,
    0,
    0,
    0,
    0,
    0,
    0,
    0,
    0,
    0,
    0,
    0,
    778,
    0,
    0,
    0,
    0,
    0,
    0,
    786,
    0,
    0,
    0,
    0,
    0,
    0,
    0,
    0,
    0,
    0,
    0,
    0,
    0,
    0,
    0,
    0,
    0,
    0,
    0,
    0,
    0,
    334,
    0,
    0,
    0,
    0,
    0,
    0,
    0,
    0,
    0,
    0,
    0,
    0,
    0,
    351,
    0,
    0,
    0,
    0,
    0,
    0,
    0,
    0,
    0,
    0,
    0,
    0,
    0,
    0,
    0,
    0,
    0,
    0,
    0,
    0,
    0,
    0,
    0,
    0,
    0,
    0,
    0,
    0,
    0,
    0,
    0,
    0,
    769,
    770,
    771,
    0,
    0,
    0,
    0,
    777,
    793,
    779,
    0,
    0,
    0,
    0,
    785,
    801,
    787,
    0,
    0,
    0,
    0,
    80,
    0,
    0,
    0,
    0,
    0,
    0,
    88,
    0,
    336,
    0,
    0,
    0,
    0,
    825,
    826,
    827,
    0,
    0,
    0,
    0,
    833,
    792,
    835,
    0,
    0,
    0,
    0,
    841,
    800,
    843,
    0,
    0,
    0,
    0,
    0,
    0,
    0,
    0,
    0,
    0,
    0,
    0,
    0,
    0,
    0,
    0,
    0,
    0,
    0,
    0,
    0,
    0,
    0,
    0,
    0,
    0,
    0,
    0,
    0,
    0,
    0,
    0,
    0,
    0,
    0,
    0,
    0,
    0,
    0,
    0,
    0,
    0,
    0,
    0,
    0,
    0,
    0,
    0,
    0,
    0,
    0,
    0,
    0,
    0,
    0,
    0,
    0,
    0,
    0,
    0,
    0,
    0,
    0,
    0,
    0,
    0,
    0,
    0,
    0,
    0,
    0,
    0,
    0,
    0,
    0,
    0,
    0,
    0,
    0,
    0,
    0,
    0,
    0,
    0,
    0,
    0,
    0,
    0,
    0,
    0,
    0,
    0,
    0,
    0,
    0,
    0,
    0,
    0,
    0,
    0,
    0,
    0,
    0,
    0,
    0,
    0,
    0,
    0,
    0,
    0,
    0,
    0,
    0,
    0,
    0,
    0,
    0,
    0,
    0,
    0,
    0,
    0,
    0,
    0,
    0,
    0,
    0,
    0,
    0,
    0,
    0,
    0,
    0,
    0,
    0,
    0,
    0,
    0,
    0,
    0,
    0,
    0,
    0,
    0,
    0,
    0,
    0,
    0,
    0,
    0,
    0,
    0,
    0,
    0,
    0,
    0,
    0,
    0,
    0,
    0,
    0,
    0,
    0,
    0,
    0,
    0,
    0,
    0,
    0,
    0,
    0,
    0,
    0,
    0,
    0,
    0,
    0,
    0,
    0,
    0,
    0,
    0,
    0,
    0
  ],
  "events": [
    null,
    {
      "id": 1,
      "name": "EV001",
      "note": "",
      "pages": [
        {
          "conditions": {
            "actorId": 1,
            "actorValid": false,
            "itemId": 1,
            "itemValid": false,
            "selfSwitchCh": "A",
            "selfSwitchValid": false,
            "switch1Id": 1,
            "switch1Valid": false,
            "switch2Id": 1,
            "switch2Valid": false,
            "variableId": 1,
            "variableValid": false,
            "variableValue": 0
          },
          "directionFix": false,
          "image": {
            "tileId": 0,
            "characterName": "",
            "direction": 2,
            "pattern": 0,
            "characterIndex": 0
          },
          "moveFrequency": 3,
          "moveRoute": {
            "list": [
              {
                "code": 0,
                "indent": null,
                "parameters": []
              }
            ],
            "repeat": true,
            "skippable": false,
            "wait": false
          },
          "moveSpeed": 3,
          "moveType": 0,
          "priorityType": 0,
          "stepAnime": false,
          "through": false,
          "trigger": 1,
          "walkAnime": true,
          "list": [
            {
              "code": 250,
              "indent": 0,
              "parameters": [
                {
                  "name": "Move1",
                  "volume": 90,
                  "pitch": 100,
                  "pan": 0
                }
              ]
            },
            {
              "code": 201,
              "indent": 0,
              "parameters": [
                0,
                34,
                8,
                10,
                2,
                0
              ]
            },
            {
              "code": 0,
              "indent": 0,
              "parameters": []
            }
          ]
        }
      ],
      "x": 3,
      "y": 9
    },
    {
      "id": 2,
      "name": "EV002",
      "note": "",
      "pages": [
        {
          "conditions": {
            "actorId": 1,
            "actorValid": false,
            "itemId": 1,
            "itemValid": false,
            "selfSwitchCh": "A",
            "selfSwitchValid": false,
            "switch1Id": 1,
            "switch1Valid": false,
            "switch2Id": 1,
            "switch2Valid": false,
            "variableId": 1,
            "variableValid": false,
            "variableValue": 0
          },
          "directionFix": true,
          "image": {
            "tileId": 0,
            "characterName": "!Chest",
            "direction": 2,
            "pattern": 0,
            "characterIndex": 6
          },
          "moveFrequency": 3,
          "moveRoute": {
            "list": [
              {
                "code": 0,
                "indent": null,
                "parameters": []
              }
            ],
            "repeat": true,
            "skippable": false,
            "wait": false
          },
          "moveSpeed": 3,
          "moveType": 0,
          "priorityType": 1,
          "stepAnime": false,
          "through": false,
          "trigger": 0,
          "walkAnime": false,
          "list": [
            {
              "code": 101,
              "indent": 0,
              "parameters": [
                "Actor4",
                2,
                0,
                2
              ]
            },
            {
              "code": 401,
              "indent": 0,
              "parameters": [
                "\\p3I don't need whatever's in there."
              ]
            },
            {
              "code": 0,
              "indent": 0,
              "parameters": []
            }
          ]
        }
      ],
      "x": 2,
      "y": 7
    },
    {
      "id": 3,
      "name": "EV003",
      "note": "",
      "pages": [
        {
          "conditions": {
            "actorId": 1,
            "actorValid": false,
            "itemId": 1,
            "itemValid": false,
            "selfSwitchCh": "A",
            "selfSwitchValid": false,
            "switch1Id": 1,
            "switch1Valid": false,
            "switch2Id": 1,
            "switch2Valid": false,
            "variableId": 1,
            "variableValid": false,
            "variableValue": 0
          },
          "directionFix": false,
          "image": {
            "tileId": 0,
            "characterName": "",
            "direction": 2,
            "pattern": 0,
            "characterIndex": 0
          },
          "moveFrequency": 3,
          "moveRoute": {
            "list": [
              {
                "code": 0,
                "indent": null,
                "parameters": []
              }
            ],
            "repeat": true,
            "skippable": false,
            "wait": false
          },
          "moveSpeed": 3,
          "moveType": 0,
          "priorityType": 0,
          "stepAnime": false,
          "through": false,
          "trigger": 1,
          "walkAnime": true,
          "list": [
            {
              "code": 250,
              "indent": 0,
              "parameters": [
                {
                  "name": "Move1",
                  "volume": 90,
                  "pitch": 100,
                  "pan": 0
                }
              ]
            },
            {
              "code": 201,
              "indent": 0,
              "parameters": [
                0,
                34,
                8,
                7,
                8,
                0
              ]
            },
            {
              "code": 0,
              "indent": 0,
              "parameters": []
            }
          ]
        }
      ],
      "x": 3,
      "y": 4
    },
    {
      "id": 4,
      "name": "EV004",
      "note": "",
      "pages": [
        {
          "conditions": {
            "actorId": 1,
            "actorValid": false,
            "itemId": 1,
            "itemValid": false,
            "selfSwitchCh": "A",
            "selfSwitchValid": false,
            "switch1Id": 1,
            "switch1Valid": false,
            "switch2Id": 1,
            "switch2Valid": false,
            "variableId": 1,
            "variableValid": false,
            "variableValue": 0
          },
          "directionFix": true,
          "image": {
            "tileId": 0,
            "characterName": "!Flame",
            "direction": 2,
            "pattern": 0,
            "characterIndex": 7
          },
          "list": [
            {
              "code": 123,
              "indent": 0,
              "parameters": [
                "A",
                0
              ]
            },
            {
              "code": 250,
              "indent": 0,
              "parameters": [
                {
                  "name": "Equip3",
                  "volume": 90,
                  "pitch": 100,
                  "pan": 0
                }
              ]
            },
            {
              "code": 126,
              "indent": 0,
              "parameters": [
                121,
                0,
                0,
                1
              ]
            },
            {
              "code": 0,
              "indent": 0,
              "parameters": []
            }
          ],
          "moveFrequency": 3,
          "moveRoute": {
            "list": [
              {
                "code": 0,
                "parameters": []
              }
            ],
            "repeat": true,
            "skippable": false,
            "wait": false
          },
          "moveSpeed": 3,
          "moveType": 0,
          "priorityType": 0,
          "stepAnime": true,
          "through": false,
          "trigger": 0,
          "walkAnime": true
        },
        {
          "conditions": {
            "actorId": 1,
            "actorValid": false,
            "itemId": 1,
            "itemValid": false,
            "selfSwitchCh": "A",
            "selfSwitchValid": true,
            "switch1Id": 1,
            "switch1Valid": false,
            "switch2Id": 1,
            "switch2Valid": false,
            "variableId": 1,
            "variableValid": false,
            "variableValue": 0
          },
          "directionFix": false,
          "image": {
            "characterIndex": 0,
            "characterName": "",
            "direction": 2,
            "pattern": 0,
            "tileId": 0
          },
          "list": [
            {
              "code": 0,
              "indent": 0,
              "parameters": []
            }
          ],
          "moveFrequency": 3,
          "moveRoute": {
            "list": [
              {
                "code": 0,
                "parameters": []
              }
            ],
            "repeat": true,
            "skippable": false,
            "wait": false
          },
          "moveSpeed": 3,
          "moveType": 0,
          "priorityType": 0,
          "stepAnime": false,
          "through": false,
          "trigger": 0,
          "walkAnime": true
        }
      ],
      "x": 4,
      "y": 5
    }
  ]
}